tmkit/.env
tmkit/Path.py
tmkit/__init__.py
tmkit/__main__.py
tmkit/base/PDB.py
tmkit/base/Position.py
tmkit/base/__init__.py
tmkit/cath.py
tmkit/chain/Collate.py
tmkit/chain/CollateBatch.py
tmkit/chain/PDB.py
tmkit/chain/__init__.py
tmkit/channel/Workbench.py
tmkit/channel/__init__.py
tmkit/collate.py
tmkit/contact/Evaluator.py
tmkit/contact/Reader.py
tmkit/contact/__init__.py
tmkit/db/Connectivity.py
tmkit/db/Reader.py
tmkit/db/__init__.py
tmkit/db/biogrid/Reader.py
tmkit/db/biogrid/__init__.py
tmkit/db/cath/Reader.py
tmkit/db/cath/__init__.py
tmkit/db/construct/Network.py
tmkit/db/construct/__init__.py
tmkit/db/intact/Reader.py
tmkit/db/intact/__init__.py
tmkit/db/muthtp/Reader.py
tmkit/db/muthtp/__init__.py
tmkit/db/predmuthtp/Reader.py
tmkit/db/predmuthtp/__init__.py
tmkit/edge.py
tmkit/feature.py
tmkit/fetch.py
tmkit/id/Fasta.py
tmkit/id/Mapping.py
tmkit/id/PDB.py
tmkit/id/__init__.py
tmkit/interface/Tool.py
tmkit/interface/Topology.py
tmkit/interface/__init__.py
tmkit/mapping.py
tmkit/msa.py
tmkit/mut.py
tmkit/name/Mapping.py
tmkit/name/__init__.py
tmkit/position/__init__.py
tmkit/position/scenario/Segment.py
tmkit/position/scenario/Separation.py
tmkit/position/scenario/__init__.py
tmkit/ppi.py
tmkit/property/HelixSurface.py
tmkit/property/__init__.py
tmkit/property/lips.pl
tmkit/qc.py
tmkit/retrieve/Fasta.py
tmkit/retrieve/MSA.py
tmkit/retrieve/PDB.py
tmkit/retrieve/XML.py
tmkit/retrieve/__init__.py
tmkit/rrc.py
tmkit/seq.py
tmkit/seqnetrr/ComputLib.py
tmkit/seqnetrr/Controller.py
tmkit/seqnetrr/__init__.py
tmkit/seqnetrr/combo/Length.py
tmkit/seqnetrr/combo/Param.py
tmkit/seqnetrr/combo/Position.py
tmkit/seqnetrr/combo/Segment.py
tmkit/seqnetrr/combo/Separation.py
tmkit/seqnetrr/combo/__init__.py
tmkit/seqnetrr/graph/Bipartite.py
tmkit/seqnetrr/graph/Cumulative.py
tmkit/seqnetrr/graph/Unipartite.py
tmkit/seqnetrr/graph/__init__.py
tmkit/seqnetrr/net/Reader.py
tmkit/seqnetrr/net/__init__.py
tmkit/seqnetrr/window/Pair.py
tmkit/seqnetrr/window/Single.py
tmkit-0.0.6.dist-info/LICENSE
tmkit-0.0.6.dist-info/METADATA
tmkit-0.0.6.dist-info/WHEEL
tmkit-0.0.6.dist-info/RECORD
