Metadata-Version: 2.3
Name: tmkit
Version: 0.0.6
Summary: 
Author: Jianfeng Sun
Author-email: jianfeng.sunmt@gmail.com
Requires-Python: >=3.11,<4.0
Classifier: Programming Language :: Python :: 3
Classifier: Programming Language :: Python :: 3.11
Classifier: Programming Language :: Python :: 3.12
Classifier: Programming Language :: Python :: 3.13
Requires-Dist: biopandas (>=0.5.1,<0.6.0)
Requires-Dist: biopython (>=1.85,<2.0)
Requires-Dist: numpy (>=2.2.4,<3.0.0)
Requires-Dist: openpyxl (>=3.1.5,<4.0.0)
Requires-Dist: pandas (>=2.2.3,<3.0.0)
Requires-Dist: pyfiglet (>=1.0.2,<2.0.0)
Requires-Dist: scikit-learn (>=1.6.1,<2.0.0)
Requires-Dist: xmltramp2 (>=3.1.1,<4.0.0)
